tiingo/__init__.py
tiingo/__version__.py
tiingo/api.py
tiingo/exceptions.py
tiingo/restclient.py
tiingo/wsclient.py
tiingo-0.15.6.dist-info/AUTHORS.rst
tiingo-0.15.6.dist-info/LICENSE
tiingo-0.15.6.dist-info/METADATA
tiingo-0.15.6.dist-info/WHEEL
tiingo-0.15.6.dist-info/top_level.txt
tiingo-0.15.6.dist-info/RECORD
