Metadata-Version: 2.1
Name: tiingo
Version: 0.15.6
Summary: REST Client for Tiingo Data Platform API
Home-page: https://github.com/hydrosquall/tiingo-python
Author: Cameron Yick
Author-email: cameron.yick@gmail.com
License: MIT license
Keywords: tiingo,finance,stocks,rest
Classifier: Development Status :: 4 - Beta
Classifier: Intended Audience :: Developers
Classifier: Intended Audience :: Financial and Insurance Industry
Classifier: License :: OSI Approved :: MIT License
Classifier: Natural Language :: English
Classifier: Topic :: Office/Business :: Financial :: Investment
Classifier: Programming Language :: Python :: 3
Classifier: Programming Language :: Python :: 3.8
Classifier: Programming Language :: Python :: 3.9
Classifier: Programming Language :: Python :: 3.10
Classifier: Programming Language :: Python :: 3.11
Classifier: Programming Language :: Python :: 3.12
License-File: LICENSE
License-File: AUTHORS.rst
Requires-Dist: requests
Requires-Dist: websocket-client
Provides-Extra: pandas
Requires-Dist: pandas >=0.18 ; extra == 'pandas'
